MANIFEST.in
README.txt
setup.cfg
setup.py
Products/__init__.py
Products.BigramSplitter.egg-info/PKG-INFO
Products.BigramSplitter.egg-info/SOURCES.txt
Products.BigramSplitter.egg-info/dependency_links.txt
Products.BigramSplitter.egg-info/entry_points.txt
Products.BigramSplitter.egg-info/namespace_packages.txt
Products.BigramSplitter.egg-info/not-zip-safe
Products.BigramSplitter.egg-info/paster_plugins.txt
Products.BigramSplitter.egg-info/requires.txt
Products.BigramSplitter.egg-info/top_level.txt
Products/BigramSplitter/BigramSplitter.py
Products/BigramSplitter/README-ja.txt
Products/BigramSplitter/__init__.py
Products/BigramSplitter/config.py
Products/BigramSplitter/configure.zcml
Products/BigramSplitter/core.py
Products/BigramSplitter/monkey.py
Products/BigramSplitter/version.txt
Products/BigramSplitter/Extensions/Install.py
Products/BigramSplitter/docs/CHANGES.txt
Products/BigramSplitter/docs/LICENSE.GPL
Products/BigramSplitter/docs/LICENSE.ZPL
Products/BigramSplitter/docs/LICENSE.txt
Products/BigramSplitter/profiles/default/catalog.xml
Products/BigramSplitter/profiles/default/metadata.xml
Products/BigramSplitter/profiles/default/skins.xml
Products/BigramSplitter/profiles/remove/catalog.xml
Products/BigramSplitter/profiles/remove/skins.xml
Products/BigramSplitter/skins/BigramSplitter/highlightsearchterms.js
Products/BigramSplitter/tests/__init__.py
Products/BigramSplitter/tests/base.py
Products/BigramSplitter/tests/testJapanese.py
Products/BigramSplitter/tests/testSetup.py
docs/HISTORY.txt
docs/INSTALL.txt
docs/LICENSE.GPL
docs/LICENSE.txt