Metadata-Version: 1.0
Name: Products.BigramSplitter
Version: 1.0
Summary: 'BigramSplitter' is add-on search product for Plone 3.x. It supports non-English languages, especially south east Asian languages.
Home-page: http://www.cmscom.jp/
Author: CMScom
Author-email: terada@cmscom.jp
License: GPL
Keywords: Plone Zope Splitter Japanese
Platform: UNKNOWN
Classifier: Framework :: Plone
Classifier: Programming Language :: Python
Classifier: Topic :: Software Development :: Libraries :: Python Modules
